inso/__init__.py
inso/astro.py
inso/figures.py
inso/inso.py
inso/minmax.py
inso/astrofiles/Laskar1993/INSOLN.LA93_01.BTL.ASC
inso/astrofiles/Laskar1993/INSOLN.LA93_11.BTL.ASC
inso/astrofiles/Laskar1993/INSOLP.LA93_01.BTL.ASC
inso/astrofiles/Laskar1993/INSOLP.LA93_11.BTL.ASC
inso/astrofiles/Laskar2004/INSOLN.LA2004.BTL.100.ASC
inso/astrofiles/Laskar2004/INSOLN.LA2004.BTL.ASC
inso/astrofiles/Laskar2004/INSOLP.LA2004.BTL.ASC
inso/astrofiles/Laskar2010/La2010a_ecc3L.dat
inso/astrofiles/Laskar2010/La2010b_ecc3L.dat
inso/astrofiles/Laskar2010/La2010c_ecc3L.dat
inso/astrofiles/Laskar2010/La2010d_ecc3L.dat
inso/astrofiles/LaskarMars2003-2004/INSOLN.LA2003.MARS.ASC
inso/astrofiles/LaskarMars2003-2004/INSOLN.LA2004.MARS.ASC
inso/astrofiles/LaskarMars2003-2004/INSOLP.LA2003.MARS.ASC
inso/astrofiles/LaskarMars2003-2004/INSOLP.LA2004.MARS.ASC
inso/astrofiles/LaskarMars2003-2004/README.TXT
inso-0.7.0.dist-info/licenses/LICENSE
inso-0.7.0.dist-info/METADATA
inso-0.7.0.dist-info/WHEEL
inso-0.7.0.dist-info/top_level.txt
inso-0.7.0.dist-info/RECORD
