Metadata-Version: 2.4
Name: inso
Version: 0.7.0
Summary: A module to compute insolation based on eccentricity, obliquity, and climatic precession parameters from various astronomical solutions (Berger 1978, Laskar 2004, ...).
Author-email: Didier Paillard <Didier.Paillard@lsce.ipsl.fr>
License-Expression: CECILL-2.1
Requires-Python: >=3.10
License-File: LICENSE
Requires-Dist: numpy>=1.26.4
Requires-Dist: scipy>=1.14.0
Requires-Dist: matplotlib>=3.8.4
Dynamic: license-file
